odoo/addons/product_dimension_volumetric_weight/README.rst
odoo/addons/product_dimension_volumetric_weight/__init__.py
odoo/addons/product_dimension_volumetric_weight/__manifest__.py
odoo/addons/product_dimension_volumetric_weight/i18n/es.po
odoo/addons/product_dimension_volumetric_weight/i18n/product_dimension_volumetric_weight.pot
odoo/addons/product_dimension_volumetric_weight/i18n/product_uom_volumetric_weight.pot
odoo/addons/product_dimension_volumetric_weight/models/__init__.py
odoo/addons/product_dimension_volumetric_weight/models/product_product.py
odoo/addons/product_dimension_volumetric_weight/models/product_template.py
odoo/addons/product_dimension_volumetric_weight/models/uom_uom.py
odoo/addons/product_dimension_volumetric_weight/readme/CONFIGURE.rst
odoo/addons/product_dimension_volumetric_weight/readme/CONTRIBUTORS.rst
odoo/addons/product_dimension_volumetric_weight/readme/DESCRIPTION.rst
odoo/addons/product_dimension_volumetric_weight/readme/USAGE.rst
odoo/addons/product_dimension_volumetric_weight/static/description/icon.png
odoo/addons/product_dimension_volumetric_weight/static/description/index.html
odoo/addons/product_dimension_volumetric_weight/tests/__init__.py
odoo/addons/product_dimension_volumetric_weight/tests/test_product_uom.py
odoo/addons/product_dimension_volumetric_weight/views/product_view.xml
odoo/addons/product_dimension_volumetric_weight/views/uom_uom_view.xml
odoo13_addon_product_dimension_volumetric_weight-13.0.1.0.1.dist-info/METADATA
odoo13_addon_product_dimension_volumetric_weight-13.0.1.0.1.dist-info/WHEEL
odoo13_addon_product_dimension_volumetric_weight-13.0.1.0.1.dist-info/top_level.txt
odoo13_addon_product_dimension_volumetric_weight-13.0.1.0.1.dist-info/RECORD
